aton/__init__.py
aton/_version.py
aton/alias.py
aton/call.py
aton/file.py
aton/api/__init__.py
aton/api/castep.py
aton/api/phonopy.py
aton/api/pwx.py
aton/api/slurm.py
aton/txt/__init__.py
aton/txt/edit.py
aton/txt/extract.py
aton/txt/find.py
aton-1.1.3.dist-info/licenses/LICENSE
tests/__init__.py
tests/test_edit.py
tests/test_extract.py
tests/test_file.py
tests/test_find.py
tests/test_pwx.py
aton-1.1.3.dist-info/METADATA
aton-1.1.3.dist-info/WHEEL
aton-1.1.3.dist-info/top_level.txt
aton-1.1.3.dist-info/RECORD
