Metadata-Version: 2.4
Name: aton
Version: 1.1.3
Summary: The Advanced Text Operations for scieNtific python (ATON) provides powerful and comprehensive text-edition tools to edit and analyse simuation data.
Author: Pablo Gila-Herranz
Author-email: pgila001@ikasle.ehu.eus
License: AGPL-3.0
Keywords: Aton,Neutron,Neutron research,Spectra,Inelastic Neutron Scattering,INS,Ab-initio,DFT,Density Functional Theory,MD,Molecular Dynamics,Quantum ESPRESSO,Phonopy,CASTEP
Classifier: Development Status :: 5 - Production/Stable
Classifier: Natural Language :: English
Classifier: Intended Audience :: Science/Research
Classifier: Programming Language :: Python :: 3
Classifier: Operating System :: POSIX :: Linux
Classifier: Operating System :: Microsoft :: Windows
Classifier: Operating System :: Other OS
Requires-Python: >=3
License-File: LICENSE
Requires-Dist: scipy
Requires-Dist: pandas
Requires-Dist: numpy
Requires-Dist: matplotlib
Requires-Dist: periodictable
Dynamic: author
Dynamic: author-email
Dynamic: classifier
Dynamic: description
Dynamic: description-content-type
Dynamic: keywords
Dynamic: license
Dynamic: license-file
Dynamic: requires-dist
Dynamic: requires-python
Dynamic: summary
